ConsulService/__init__.py
ConsulService/apps.py
ConsulService/settings.py
ConsulService/tests.py
ConsulService/urls.py
ConsulService/utils.py
ConsulService/views.py
ConsulService/migrations/__init__.py
django_consul-0.4.0.dist-info/METADATA
django_consul-0.4.0.dist-info/WHEEL
django_consul-0.4.0.dist-info/top_level.txt
django_consul-0.4.0.dist-info/RECORD
