Metadata-Version: 2.1
Name: django-consul
Version: 0.4.0
Summary: A django app which register django service to consul server.
Home-page: 
Author: Xujia Li
Author-email: lixujiacn@outlook.com
Classifier: Programming Language :: Python :: 3
Classifier: License :: OSI Approved :: MIT License
Classifier: Operating System :: OS Independent
Requires-Python: >=3.6
Requires-Dist: Django
Requires-Dist: requests
